README.md
setup.cfg
setup.py
simple_model_logging/__init__.py
simple_model_logging/date_encoder.py
simple_model_logging/json_utils.py
simple_model_logging/models.py
simple_model_logging/simple_model_logging.py
simple_model_logging/test.py
simple_model_logging.egg-info/PKG-INFO
simple_model_logging.egg-info/SOURCES.txt
simple_model_logging.egg-info/dependency_links.txt
simple_model_logging.egg-info/not-zip-safe
simple_model_logging.egg-info/top_level.txt